falguard.py
falguard-0.4.dist-info/LICENSE
falguard-0.4.dist-info/METADATA
falguard-0.4.dist-info/WHEEL
falguard-0.4.dist-info/top_level.txt
falguard-0.4.dist-info/RECORD
