Metadata-Version: 2.1
Name: falguard
Version: 0.4
Summary: Falcon requests validation against OpenAPI (Swagger) schema
Home-page: https://github.com/gwaramadze/falguard
Author: Remy Gwaramadze
Author-email: remy@gwaramadze.com
License: Apache 2.0
Platform: UNKNOWN
Classifier: Development Status :: 5 - Production/Stable
Classifier: Intended Audience :: Developers
Classifier: Operating System :: OS Independent
Classifier: Programming Language :: Python
Classifier: Programming Language :: Python :: 2
Classifier: Programming Language :: Python :: 2.7
Classifier: Programming Language :: Python :: 3
Classifier: Programming Language :: Python :: 3.4
Classifier: Programming Language :: Python :: 3.5
Classifier: Programming Language :: Python :: 3.6
Classifier: Programming Language :: Python :: 3.7
Classifier: Programming Language :: Python :: 3.8
Classifier: Topic :: Software Development :: Libraries
Requires-Dist: falcon (<3.0.0,>=1.1.0)
Requires-Dist: bravado-core (<6.0.0,>=4.6.0)
Requires-Dist: six (>=1.12.0)
Provides-Extra: tests
Requires-Dist: pytest ; extra == 'tests'
Requires-Dist: pytest-cov ; extra == 'tests'
Requires-Dist: pytest-flake8 ; extra == 'tests'
Requires-Dist: pytest-pylint ; extra == 'tests'
